aws_role_switcher/__init__.py
aws_role_switcher/main.py
aws_role_switcher-1.5.0.data/scripts/aws-role-switcher
aws_role_switcher-1.5.0.data/scripts/aws-role-switcher.sh
aws_role_switcher-1.5.0.dist-info/LICENSE.txt
aws_role_switcher-1.5.0.dist-info/METADATA
aws_role_switcher-1.5.0.dist-info/WHEEL
aws_role_switcher-1.5.0.dist-info/top_level.txt
aws_role_switcher-1.5.0.dist-info/RECORD
