Metadata-Version: 2.1
Name: aws-role-switcher
Version: 1.5.0
Summary: This is a CLI application to switch your role using autocompletion by parsing your config/credential file and set environment variables
Home-page: UNKNOWN
Author: Elijah Roberts
Author-email: elijah@elijahjamesroberts.com
License: MIT
Download-URL: https://github.com/elijah-roberts/aws-role-switcher/archive/1.4.0.tar.gz
Keywords: AWS,ROLE,GIT,PROFILE,AUTOCOMPLETE
Platform: UNKNOWN
Classifier: Programming Language :: Python :: 3
Classifier: License :: OSI Approved :: MIT License
Classifier: Operating System :: OS Independent
Requires-Python: >=3.6
License-File: LICENSE.txt
Requires-Dist: prompt-toolkit
Requires-Dist: setuptools
